MANIFEST.in
README.txt
setup.py
KatoAdhocExpress.egg-info/PKG-INFO
KatoAdhocExpress.egg-info/SOURCES.txt
KatoAdhocExpress.egg-info/dependency_links.txt
KatoAdhocExpress.egg-info/requires.txt
KatoAdhocExpress.egg-info/top_level.txt
katoAdhocExpress/__init__.py
katoAdhocExpress/kato.py