Metadata-Version: 1.0
Name: KatoAdhocExpress
Version: 0.9
Summary: Kato Adhoc Express
Home-page: https://kato.im/
Author: Elvis
Author-email: elvis@maestraslolutions.com
License: BSD
Platform: UNKNOWN
